lab_data_utils-0.1.0.dist-info/licenses/LICENSE
labdatautils/__init__.py
labdatautils/error_propagation.py
labdatautils/latex_report.py
lab_data_utils-0.1.0.dist-info/METADATA
lab_data_utils-0.1.0.dist-info/WHEEL
lab_data_utils-0.1.0.dist-info/top_level.txt
lab_data_utils-0.1.0.dist-info/RECORD
