Metadata-Version: 2.4
Name: lab-data-utils
Version: 0.1.0
Summary: Experimental data utilities: error propagation and LaTeX table generator
Author-email: Pablo Castro Perez <pbl.castroperez@gmail.com>
License: MIT
Project-URL: Homepage, https://github.com/Pablo-CastroPerez/lab-data-utils
Project-URL: BugTracker, https://github.com/Pablo-CastroPerez/lab-data-utils/issues
Classifier: Programming Language :: Python :: 3
Classifier: Programming Language :: Python :: 3 :: Only
Classifier: License :: OSI Approved :: MIT License
Classifier: Operating System :: OS Independent
Classifier: Intended Audience :: Science/Research
Classifier: Topic :: Scientific/Engineering
Requires-Python: >=3.8
License-File: LICENSE
Requires-Dist: numpy>=1.22
Dynamic: license-file
